LICENSE
README.md
pyproject.toml
setup.py
pysensmcda/__init__.py
pysensmcda/calculate_preference.py
pysensmcda/utils.py
pysensmcda/validator.py
pysensmcda.egg-info/PKG-INFO
pysensmcda.egg-info/SOURCES.txt
pysensmcda.egg-info/dependency_links.txt
pysensmcda.egg-info/requires.txt
pysensmcda.egg-info/top_level.txt
pysensmcda/alternative/__init__.py
pysensmcda/alternative/discrete.py
pysensmcda/alternative/percentage.py
pysensmcda/alternative/range.py
pysensmcda/alternative/removal.py
pysensmcda/compromise/HQ_compromise.py
pysensmcda/compromise/ICRA.py
pysensmcda/compromise/__init__.py
pysensmcda/compromise/borda.py
pysensmcda/compromise/dominance_directed_graph.py
pysensmcda/compromise/improved_borda.py
pysensmcda/compromise/rank_position.py
pysensmcda/criteria/__init__.py
pysensmcda/criteria/identification.py
pysensmcda/criteria/percentage.py
pysensmcda/criteria/range.py
pysensmcda/criteria/removal.py
pysensmcda/criteria/scenarios.py
pysensmcda/criteria/random_distribution/__init__.py
pysensmcda/criteria/random_distribution/chisquare_distribution.py
pysensmcda/criteria/random_distribution/laplace_distribution.py
pysensmcda/criteria/random_distribution/normal_distribution.py
pysensmcda/criteria/random_distribution/random_distribution.py
pysensmcda/criteria/random_distribution/triangular_distribution.py
pysensmcda/criteria/random_distribution/uniform_distribution.py
pysensmcda/graphs/__init__.py
pysensmcda/graphs/heatmap.py
pysensmcda/graphs/pd_ranking_graph.py
pysensmcda/graphs/preference_distribution.py
pysensmcda/graphs/rankings_distribution.py
pysensmcda/graphs/values_distribution.py
pysensmcda/graphs/weights_barplot.py
pysensmcda/probabilistic/__init__.py
pysensmcda/probabilistic/monte_carlo_weights.py
pysensmcda/probabilistic/perturbed_matrix.py
pysensmcda/probabilistic/perturbed_weights.py
pysensmcda/ranking/__init__.py
pysensmcda/ranking/alteration.py
pysensmcda/ranking/demotion.py
pysensmcda/ranking/fuzzy_ranking.py
pysensmcda/ranking/promotion.py
tests/test_calculate_preference.py
tests/test_validator.py