Metadata-Version: 2.1
Name: pysensmcda
Version: 1.0.0
Summary: Python Sensitivity Analysis Multi-Criteria Decision Analysis Package
Home-page: https://github.com/jwieckowski/pysensmcda
Author: Jakub Więckowski, Bartosz Paradowski
Author-email: Jakub Więckowski <j.wieckowski@il-pib.pl>, Bartosz Paradowski <b.paradowski@il-pib.pl>
Maintainer-email: Jakub Więckowski <j.wieckowski@il-pib.pl>, Bartosz Paradowski <b.paradowski@il-pib.pl>
Project-URL: Homepage, https://github.com/jwieckowski/pysensmcda
Project-URL: Bug Reports, https://github.com/jwieckowski/pysensmcda/issues
Project-URL: Source, https://github.com/jwieckowski/pysensmcda
Keywords: sensitivity analysis,decision-making,python,mcda,robustness
Classifier: Development Status :: 3 - Alpha
Classifier: Programming Language :: Python
Classifier: License :: OSI Approved :: MIT License
Classifier: Programming Language :: Python :: 3.10
Requires-Python: >=3.10
License-File: LICENSE
